owm_legacy/__init__.py
owm_legacy/apps.py
owm_legacy/settings.py
owm_legacy/tests.py
owm_legacy/urls.py
owm_legacy/utils.py
owm_legacy/views.py
owm_legacy/__pycache__/__init__.cpython-38.pyc
django_owm_legacy-1.1.dist-info/LICENSE
django_owm_legacy-1.1.dist-info/METADATA
django_owm_legacy-1.1.dist-info/WHEEL
django_owm_legacy-1.1.dist-info/top_level.txt
django_owm_legacy-1.1.dist-info/RECORD
