Metadata-Version: 2.1
Name: django-owm-legacy
Version: 1.1
Summary: Legacy features of OpenWISP Manager reimplemented in django
Home-page: https://github.com/openwisp/django-owm-legacy
Download-URL: https://github.com/openwisp/django-owm-legacy/releases
Author: Federico Capoano
Author-email: support@openwisp.io
License: GPL3
Keywords: django,openwisp,openwrt,networking
Platform: Platform Indipendent
Classifier: Development Status :: 5 - Production/Stable 
Classifier: Environment :: Web Environment
Classifier: Topic :: Internet :: WWW/HTTP
Classifier: Intended Audience :: Developers
Classifier: License :: OSI Approved :: MIT License
Classifier: Operating System :: OS Independent
Classifier: Framework :: Django
Classifier: Topic :: System :: Networking
Classifier: Programming Language :: Python :: 2.7
Classifier: Programming Language :: Python :: 3.4
License-File: LICENSE
Requires-Dist: openwisp-controller<1.2.0,>=1.0.0
